{
  "data": [
    {
      "id": 1,
      "page": 1,
      "title": "item 1",
      "description": "I am a description for item 1",
      "top": "10%",
      "right": "20%",
      "left": "10%",
      "bottom": "70%"
    },
    {
      "id": 2,
      "page": 1,
      "title": "item 2",
      "description": "I am a description for item 2 with a <a href='www.google.com'>link</a>",
      "top": "50%",
      "right": "10%",
      "left": "40%",
      "bottom": "10%"
    },
    {
      "id": 3,
      "page": 2,
      "title": "item 3",
      "description": "I am a description for item 3",
      "top": "1%",
      "right": "10%",
      "left": "40%",
      "bottom": "91%"
    }
  ]
}
